cashifypythondbsecret/__init__.py
cashifypythondbsecret-0.0.1.dist-info/LICENSE
cashifypythondbsecret-0.0.1.dist-info/METADATA
cashifypythondbsecret-0.0.1.dist-info/WHEEL
cashifypythondbsecret-0.0.1.dist-info/top_level.txt
cashifypythondbsecret-0.0.1.dist-info/RECORD
