Metadata-Version: 2.1
Name: cashifypythondbsecret
Version: 0.0.1
Summary: Get DB Secrets
Home-page: https://github.com/saket-cashify/cashify-python-db-secret
Author: Saket Agarwal
Author-email: saket.a@cashify.in
License: unlicense
Platform: UNKNOWN
